protollm_worker/__init__.py
protollm_worker/config.py
protollm_worker/models/__init__.py
protollm_worker/models/base.py
protollm_worker/models/cpp_models.py
protollm_worker/models/hf_models.py
protollm_worker/models/open_api_llm.py
protollm_worker/models/README.md
protollm_worker/models/vllm_models.py
protollm_worker/services/__init__.py
protollm_worker/services/broker.py
protollm_worker-1.0.5.dist-info/METADATA
protollm_worker-1.0.5.dist-info/WHEEL
protollm_worker-1.0.5.dist-info/RECORD
