Metadata-Version: 2.3
Name: protollm-worker
Version: 1.0.5
Summary: 
Author: aimclub
Requires-Python: >=3.10,<4.0
Classifier: Programming Language :: Python :: 3
Classifier: Programming Language :: Python :: 3.10
Classifier: Programming Language :: Python :: 3.11
Classifier: Programming Language :: Python :: 3.12
Classifier: Programming Language :: Python :: 3.13
Requires-Dist: pika (>=1.3.2,<2.0.0)
Requires-Dist: protollm_sdk (>=1.1.6,<2.0.0)
Requires-Dist: pydantic (>=2.7.4,<3.0.0)
Requires-Dist: redis (>=5.0.5,<6.0.0)
